one_hot_quiz/one_hot.v
module one_hot(in, valid);
input  [3:0] in;
output reg valid;

always @(*)
    valid = (in != 0) && ((in & (in - 1)) == 0);

endmodule


// Case-based approach — easier to read
// // module one_hot(in, valid);
// // input  [3:0] in;
// // output reg valid;
// // 
// // always @(*) begin
// //     case (in)
// //         4'b0001, 4'b0010,
// //         4'b0100, 4'b1000: valid = 1;
// //         default:          valid = 0;
// //     endcase
// // end
// // 
// // endmodule

one_hot_quiz/tb_one_hot.v
module tb_one_hot;

    reg [3:0] in;
    wire valid;

    one_hot uut (
        .in(in),
        .valid(valid)
    );

    initial begin
        $dumpfile("tb_one_hot.vcd");
        $dumpvars(0, tb_one_hot);

        $monitor("in=%b  valid=%b", in, valid);

        in = 4'b0000; #10;
        in = 4'b0001; #10;
        in = 4'b0010; #10;
        in = 4'b0011; #10;
        in = 4'b0100; #10;
        in = 4'b0101; #10;
        in = 4'b0110; #10;
        in = 4'b0111; #10;
        in = 4'b1000; #10;
        in = 4'b1001; #10;
        in = 4'b1010; #10;
        in = 4'b1011; #10;
        in = 4'b1100; #10;
        in = 4'b1101; #10;
        in = 4'b1110; #10;
        in = 4'b1111; #10;
        $finish;
    end
endmodule

one_hot_quiz/tb_one_hot.vcd
$date
	Wed Feb 25 07:19:40 2026
$end
$version
	Icarus Verilog
$end
$timescale
	1s
$end
$scope module tb_one_hot $end
$var wire 1 ! valid $end
$var reg 4 " in [3:0] $end
$scope module uut $end
$var wire 4 # in [3:0] $end
$var reg 1 ! valid $end
$upscope $end
$upscope $end
$enddefinitions $end
#0
$dumpvars
b0 #
b0 "
0!
$end
#10
1!
b1 "
b1 #
#20
b10 "
b10 #
#30
0!
b11 "
b11 #
#40
1!
b100 "
b100 #
#50
0!
b101 "
b101 #
#60
b110 "
b110 #
#70
b111 "
b111 #
#80
1!
b1000 "
b1000 #
#90
0!
b1001 "
b1001 #
#100
b1010 "
b1010 #
#110
b1011 "
b1011 #
#120
b1100 "
b1100 #
#130
b1101 "
b1101 #
#140
b1110 "
b1110 #
#150
b1111 "
b1111 #
