LAB5/src/ALU.v
module ALU(A, B, sel, result);
    input [31:0] A, B;
    input [3:0] sel;
    output reg [31:0] result;

    always @(*) begin
        case (sel)
            4'b0000: result = A & B;
            4'b0001: result = A | B;
            4'b0010: result = A + B;
            4'b0011: result = A ^ B;
            4'b0100: result = A << B[4:0];
            4'b0101: result = A >> B[4:0];
            4'b0110: result = A - B;
            4'b0111: result = $signed(A) >>> B[4:0];
            4'b1000: result = ($signed(A) < $signed(B)) ? 32'd1 : 32'd0;
            4'b1001: result = (A < B) ? 32'd1 : 32'd0;
            default: result = 32'd0;
        endcase
    end
endmodule

LAB5/src/tb_ALU.v
`timescale 1ns / 1ps

module tb_ALU;

    reg [31:0] A;
    reg [31:0] B;
    reg [3:0] sel;

    wire [31:0] result;

    ALU uut (
        .A(A),
        .B(B),
        .sel(sel),
        .result(result)
    );

    initial begin
        $dumpfile("../waveform/tb_ALU.vcd");
        $dumpvars(0, tb_ALU);
        $monitor("A: %h | B: %h | sel: %b | result: %h", A, B, sel, result);

        A = 32'hAAAAAAAA; B = 32'h55555555; sel = 4'b0000; #10;
        A = 32'hAAAAAAAA; B = 32'h55555555; sel = 4'b0001; #10;
        A = 32'd10; B = 32'd20; sel = 4'b0010; #10;
        A = 32'hAAAAAAAA; B = 32'h55555555; sel = 4'b0011; #10;
        A = 32'h00000001; B = 32'd5; sel = 4'b0100; #10;
        A = 32'h80000000; B = 32'd1; sel = 4'b0101; #10;
        A = 32'd30; B = 32'd10; sel = 4'b0110; #10;
        A = 32'h80000000; B = 32'd1; sel = 4'b0111; #10;
        A = 32'hFFFFFFFF; B = 32'd0; sel = 4'b1000; #10;
        A = 32'd0; B = 32'hFFFFFFFF; sel = 4'b1000; #10;
        A = 32'hFFFFFFFF; B = 32'd0; sel = 4'b1001; #10;
        A = 32'd0; B = 32'hFFFFFFFF; sel = 4'b1001; #10;
        sel = 4'b1111; #10;

        $stop;
    end

endmodule

LAB5/waveform/tb_ALU.vcd
$date
	Thu Mar 12 11:59:17 2026
$end
$version
	Icarus Verilog
$end
$timescale
	1ps
$end
$scope module tb_ALU $end
$var wire 32 ! result [31:0] $end
$var reg 32 " A [31:0] $end
$var reg 32 # B [31:0] $end
$var reg 4 $ sel [3:0] $end
$scope module uut $end
$var wire 32 % A [31:0] $end
$var wire 32 & B [31:0] $end
$var wire 4 ' sel [3:0] $end
$var reg 32 ( result [31:0] $end
$upscope $end
$upscope $end
$enddefinitions $end
#0
$dumpvars
b0 (
b0 '
b1010101010101010101010101010101 &
b10101010101010101010101010101010 %
b0 $
b1010101010101010101010101010101 #
b10101010101010101010101010101010 "
b0 !
$end
#10000
b11111111111111111111111111111111 (
b11111111111111111111111111111111 !
b1 $
b1 '
#20000
b11110 (
b11110 !
b10 $
b10 '
b10100 #
b10100 &
b1010 "
b1010 %
#30000
b11111111111111111111111111111111 (
b11111111111111111111111111111111 !
b11 $
b11 '
b1010101010101010101010101010101 #
b1010101010101010101010101010101 &
b10101010101010101010101010101010 "
b10101010101010101010101010101010 %
#40000
b100000 (
b100000 !
b100 $
b100 '
b101 #
b101 &
b1 "
b1 %
#50000
b1000000000000000000000000000000 (
b1000000000000000000000000000000 !
b101 $
b101 '
b1 #
b1 &
b10000000000000000000000000000000 "
b10000000000000000000000000000000 %
#60000
b10100 (
b10100 !
b110 $
b110 '
b1010 #
b1010 &
b11110 "
b11110 %
#70000
b11000000000000000000000000000000 (
b11000000000000000000000000000000 !
b111 $
b111 '
b1 #
b1 &
b10000000000000000000000000000000 "
b10000000000000000000000000000000 %
#80000
b1 (
b1 !
b1000 $
b1000 '
b0 #
b0 &
b11111111111111111111111111111111 "
b11111111111111111111111111111111 %
#90000
b0 (
b0 !
b11111111111111111111111111111111 #
b11111111111111111111111111111111 &
b0 "
b0 %
#100000
b1001 $
b1001 '
b0 #
b0 &
b11111111111111111111111111111111 "
b11111111111111111111111111111111 %
#110000
b1 (
b1 !
b11111111111111111111111111111111 #
b11111111111111111111111111111111 &
b0 "
b0 %
#120000
b0 (
b0 !
b1111 $
b1111 '
