LAB5/src/ALUCtrl.v
module ALUCtrl(
    input [6:0] funct7,
    input [2:0] funct3,
    output reg [3:0] alu_ctrl
);

always @(*) begin
    case({funct7, funct3})
        10'b0000000_000: alu_ctrl = 4'b0010;
        10'b0100000_000: alu_ctrl = 4'b0110;
        10'b0000000_111: alu_ctrl = 4'b0000;
        10'b0000000_110: alu_ctrl = 4'b0001;
        10'b0000000_100: alu_ctrl = 4'b0011;
        10'b0000000_001: alu_ctrl = 4'b0100;
        10'b0000000_101: alu_ctrl = 4'b0101;
        10'b0100000_101: alu_ctrl = 4'b0111;
        10'b0000000_010: alu_ctrl = 4'b1000;
        10'b0000000_011: alu_ctrl = 4'b1001;
        default: alu_ctrl = 4'b0000;
    endcase
end

endmodule

LAB5/src/tb_ALUCtrl.v
`timescale 1ns / 1ps

module tb_ALUCtrl;

    reg [6:0] funct7;
    reg [2:0] funct3;

    wire [3:0] alu_ctrl;

    ALUCtrl uut (
        .funct7(funct7),
        .funct3(funct3),
        .alu_ctrl(alu_ctrl)
    );

    initial begin
        $dumpfile("../waveform/tb_ALUCtrl.vcd");
        $dumpvars(0, tb_ALUCtrl);
        $monitor("funct7: %b | funct3: %b | alu_ctrl: %b", funct7, funct3, alu_ctrl);

        funct7 = 7'b0000000; funct3 = 3'b000; #10;
        funct7 = 7'b0100000; funct3 = 3'b000; #10;
        funct7 = 7'b0000000; funct3 = 3'b111; #10;
        funct7 = 7'b0000000; funct3 = 3'b110; #10;
        funct7 = 7'b0000000; funct3 = 3'b100; #10;
        funct7 = 7'b0000000; funct3 = 3'b001; #10;
        funct7 = 7'b0000000; funct3 = 3'b101; #10;
        funct7 = 7'b0100000; funct3 = 3'b101; #10;
        funct7 = 7'b0000000; funct3 = 3'b010; #10;
        funct7 = 7'b0000000; funct3 = 3'b011; #10;
        funct7 = 7'b1111111; funct3 = 3'b111; #10;

        $stop;
    end

endmodule

LAB5/waveform/tb_ALUCtrl.vcd
$date
	Thu Mar 12 12:18:08 2026
$end
$version
	Icarus Verilog
$end
$timescale
	1ps
$end
$scope module tb_ALUCtrl $end
$var wire 4 ! alu_ctrl [3:0] $end
$var reg 3 " funct3 [2:0] $end
$var reg 7 # funct7 [6:0] $end
$scope module uut $end
$var wire 3 $ funct3 [2:0] $end
$var wire 7 % funct7 [6:0] $end
$var reg 4 & alu_ctrl [3:0] $end
$upscope $end
$upscope $end
$enddefinitions $end
#0
$dumpvars
b10 &
b0 %
b0 $
b0 #
b0 "
b10 !
$end
#10000
b110 &
b110 !
b100000 #
b100000 %
#20000
b0 &
b0 !
b111 "
b111 $
b0 #
b0 %
#30000
b1 &
b1 !
b110 "
b110 $
#40000
b11 &
b11 !
b100 "
b100 $
#50000
b100 &
b100 !
b1 "
b1 $
#60000
b101 &
b101 !
b101 "
b101 $
#70000
b111 &
b111 !
b100000 #
b100000 %
#80000
b1000 &
b1000 !
b10 "
b10 $
b0 #
b0 %
#90000
b1001 &
b1001 !
b11 "
b11 $
#100000
b0 &
b0 !
b111 "
b111 $
b1111111 #
b1111111 %
