LAB5/src/pc.v
module pc(
    input        clk, rst,
    input        branch,
    input  [31:0] branch_target,
    output reg [31:0] pc
);

    always @(posedge clk) begin
        if (rst)
            pc <= 32'd0;
        else if (branch)
            pc <= branch_target;
        else
            pc <= pc + 32'd4;
    end

endmodule

LAB5/src/tb_pc.v
module tb_pc;

    reg        clk, rst, branch;
    reg  [31:0] branch_target;
    wire [31:0] pc;

    pc uut (
        .clk(clk),
        .rst(rst),
        .branch(branch),
        .branch_target(branch_target),
        .pc(pc)
    );

    initial clk = 0;
    always #5 clk = ~clk;

    initial begin
        $dumpfile("../waveform/tb_pc.vcd");
        $dumpvars(0, tb_pc);
        $monitor("pc: %0d", pc);

        rst = 1; branch = 0; branch_target = 0; #10;
        rst = 0;

        #10; #10; #10;

        branch = 1; branch_target = 32'd32; #10;
        branch = 0;

        #10; #10;

        $stop;
    end

endmodule

LAB5/waveform/tb_pc.vcd
$date
	Thu Mar 12 11:59:17 2026
$end
$version
	Icarus Verilog
$end
$timescale
	1ps
$end
$scope module tb_pc $end
$var wire 32 ! pc [31:0] $end
$var reg 1 " branch $end
$var reg 32 # branch_target [31:0] $end
$var reg 1 $ clk $end
$var reg 1 % rst $end
$scope module uut $end
$var wire 1 & branch $end
$var wire 32 ' branch_target [31:0] $end
$var wire 1 ( clk $end
$var wire 1 ) rst $end
$var reg 32 * pc [31:0] $end
$upscope $end
$upscope $end
$enddefinitions $end
#0
$dumpvars
bx *
1)
0(
b0 '
0&
1%
0$
b0 #
0"
bx !
$end
#5000
b0 *
b0 !
1$
1(
#10000
0$
0(
0%
0)
#15000
b100 *
b100 !
1$
1(
#20000
0$
0(
#25000
b1000 *
b1000 !
1$
1(
#30000
0$
0(
#35000
b1100 *
b1100 !
1$
1(
#40000
0$
0(
b100000 #
b100000 '
1"
1&
#45000
b100000 *
b100000 !
1$
1(
#50000
0$
0(
0"
0&
#55000
b100100 *
b100100 !
1$
1(
#60000
0$
0(
#65000
b101000 *
b101000 !
1$
1(
