LAB2/encoder8to3/encoder8to3behavioral.v
module encoder8to3behavioral (
    input [7:0] I,
    output reg [2:0] Y
);

always @(*) begin
    case (I)
        8'b00000001: Y = 3'b000;
        8'b00000010: Y = 3'b001;
        8'b00000100: Y = 3'b010;
        8'b00001000: Y = 3'b011;
        8'b00010000: Y = 3'b100;
        8'b00100000: Y = 3'b101;
        8'b01000000: Y = 3'b110;
        8'b10000000: Y = 3'b111;
        default: Y = 3'bxxx;
    endcase
end

endmodule

LAB2/encoder8to3/tb_encoder8to3behavioral.v
module tb_encoder8to3behavioral;

    reg [7:0] I;
    wire [2:0] Y;

    encoder8to3behavioral uut (
        .I(I),
        .Y(Y)
    );

    initial begin
        $dumpfile("tb_encoder8to3behavioral.vcd");
        $dumpvars(0, tb_encoder8to3behavioral);

        $monitor("I=%b | Y=%b", I, Y);

        I = 8'b00000001; #10;
        I = 8'b00000010; #10;
        I = 8'b00000100; #10;
        I = 8'b00001000; #10;
        I = 8'b00010000; #10;
        I = 8'b00100000; #10;
        I = 8'b01000000; #10;
        I = 8'b10000000; #10;

        $finish;
    end

endmodule

LAB2/encoder8to3/tb_encoder8to3behavioral.vcd
$date
	Fri Mar 06 10:54:05 2026
$end
$version
	Icarus Verilog
$end
$timescale
	1s
$end
$scope module tb_encoder8to3behavioral $end
$var wire 3 ! Y [2:0] $end
$var reg 8 " I [7:0] $end
$scope module uut $end
$var wire 8 # I [7:0] $end
$var reg 3 $ Y [2:0] $end
$upscope $end
$upscope $end
$enddefinitions $end
#0
$dumpvars
b0 $
b1 #
b1 "
b0 !
$end
#10
b1 $
b1 !
b10 "
b10 #
#20
b10 $
b10 !
b100 "
b100 #
#30
b11 $
b11 !
b1000 "
b1000 #
#40
b100 $
b100 !
b10000 "
b10000 #
#50
b101 $
b101 !
b100000 "
b100000 #
#60
b110 $
b110 !
b1000000 "
b1000000 #
#70
b111 $
b111 !
b10000000 "
b10000000 #
