LAB3/edgeDetector/edgeDetector.v
module edge_detector (
    input clk,
    input rst,
    input sig,
    output rise_pulse,
    output fall_pulse
);

reg sig_prev;

always @(posedge clk or posedge rst)
    if (rst)
        sig_prev <= 1'b0;
    else
        sig_prev <= sig;

    assign rise_pulse = sig & ~sig_prev;
    assign fall_pulse = ~sig & sig_prev;

endmodule

LAB3/edgeDetector/tb_edgeDetector.v
module tb_edge_detector;

reg clk, rst, sig;
wire rise_pulse, fall_pulse;

edge_detector uut (
    .clk(clk),
    .rst(rst),
    .sig(sig),
    .rise_pulse(rise_pulse),
    .fall_pulse(fall_pulse)
);

always #5 clk = ~clk;

always @(posedge clk)
    $display("sig=%b | rise_pulse=%b | fall_pulse=%b", sig, rise_pulse, fall_pulse);

initial begin
    clk = 0; rst = 1; sig = 0;
    #12 rst = 0;

    #10 sig = 1;
    #20 sig = 0;
    #20 sig = 1;
    #10 sig = 0;
    #20 $finish;
end

endmodule

LAB3/edgeDetector/tb_edge_detector.vcd
$date
	Tue Mar 03 08:02:28 2026
$end
$version
	Icarus Verilog
$end
$timescale
	1s
$end
$scope module tb_edge_detector $end
$var wire 1 ! fall_pulse $end
$var wire 1 " rise_pulse $end
$var reg 1 # clk $end
$var reg 1 $ rst $end
$var reg 1 % sig $end
$scope module uut $end
$var wire 1 & clk $end
$var wire 1 ! fall_pulse $end
$var wire 1 " rise_pulse $end
$var wire 1 ' rst $end
$var wire 1 ( sig $end
$var reg 1 ) sig_prev $end
$upscope $end
$upscope $end
$enddefinitions $end
#0
$dumpvars
0)
0(
1'
0&
0%
1$
0#
0"
0!
$end
#5
1#
1&
#10
0#
0&
#12
0$
0'
#15
1#
1&
#20
0#
0&
#22
1"
1%
1(
#25
0"
1)
1#
1&
#30
0#
0&
#35
1#
1&
#40
0#
0&
#42
1!
0%
0(
#45
0!
0)
1#
1&
#50
0#
0&
#55
1#
1&
#60
0#
0&
#62
1"
1%
1(
#65
0"
1)
1#
1&
#70
0#
0&
#72
1!
0%
0(
#75
0!
0)
1#
1&
